BankPy/BankPy.py
BankPy/Connect.py
BankPy/Create.py
BankPy/Delete.py
BankPy/Execute.py
BankPy/Howmate.py
BankPy/Variables.py
BankPy/__init__.py
BANK_PY-1.0.6.dist-info/METADATA
BANK_PY-1.0.6.dist-info/WHEEL
BANK_PY-1.0.6.dist-info/license
BANK_PY-1.0.6.dist-info/top_level.txt
BANK_PY-1.0.6.dist-info/RECORD
