Metadata-Version: 2.1
Name: BANK-PY
Version: 1.0.6
Summary: Armazene Seu Dados Sem Perde nada :)
Home-page: https://starcomicstar.weebly.com/
Author: José Alexsandro
Author-email: eujosealexsandro@gmail.com
License: UNKNOWN
Platform: UNKNOWN
Classifier: Programming Language :: Python :: 3
Classifier: License :: OSI Approved :: MIT License
Classifier: Operating System :: OS Independent
Requires-Python: >=3.6
